{
  "empresa": {
    "ticker": "DIRR",
    "nome": "DIRECIONAL ENGENHARIA S.A.",
    "cnpj": "16.614.075/0001-00"
  },
  "ultima_atualizacao": "2026-01-02T09:21:04.829248",
  "total_noticias": 5,
  "noticias": [
    {
      "data": "2025-12-10",
      "data_hora": "2025-12-10 18:50:43",
      "titulo": "NM)  Fato Relevante  10/12/25 (N)",
      "headline": "DIRECIONAL (DIRR-NM) - Fato Relevante - 10/12/25 (N)",
      "conteudo": null,
      "url": "https://sistemasweb.b3.com.br/PlantaoNoticias/Noticias/Detail?idNoticia=3165930&agencia=18&dataNoticia=2025-12-10%2018:50:43",
      "id": 3165930,
      "categoria": "Fato Relevante"
    },
    {
      "data": "2025-12-10",
      "data_hora": "2025-12-10 18:44:16",
      "titulo": "NM)  Fato Relevante  10/12/25",
      "headline": "DIRECIONAL (DIRR-NM) - Fato Relevante - 10/12/25",
      "conteudo": null,
      "url": "https://sistemasweb.b3.com.br/PlantaoNoticias/Noticias/Detail?idNoticia=3165922&agencia=18&dataNoticia=2025-12-10%2018:44:16",
      "id": 3165922,
      "categoria": "Fato Relevante"
    },
    {
      "data": "2025-12-10",
      "data_hora": "2025-12-10 18:37:51",
      "titulo": "NM)  Ata Reuniao do Conselho de Administracao  10/12/25",
      "headline": "DIRECIONAL (DIRR-NM) - Ata Reuniao do Conselho de Administracao - 10/12/25",
      "conteudo": null,
      "url": "https://sistemasweb.b3.com.br/PlantaoNoticias/Noticias/Detail?idNoticia=3165904&agencia=18&dataNoticia=2025-12-10%2018:37:51",
      "id": 3165904,
      "categoria": "Governança"
    },
    {
      "data": "2025-12-10",
      "data_hora": "2025-12-10 18:02:12",
      "titulo": "NM)  VM Posicao Individual (Cia,Controladas e Coligadas)",
      "headline": "DIRECIONAL (DIRR-NM) - VM Posicao Individual (Cia,Controladas e Coligadas)",
      "conteudo": null,
      "url": "https://sistemasweb.b3.com.br/PlantaoNoticias/Noticias/Detail?idNoticia=3165588&agencia=18&dataNoticia=2025-12-10%2018:02:12",
      "id": 3165588,
      "categoria": "Outros"
    },
    {
      "data": "2025-12-10",
      "data_hora": "2025-12-10 09:18:05",
      "titulo": "NM)  Calendario de Eventos Corporativos  ate 31/12/26",
      "headline": "DIRECIONAL (DIRR-NM) - Calendario de Eventos Corporativos - ate 31/12/26",
      "conteudo": null,
      "url": "https://sistemasweb.b3.com.br/PlantaoNoticias/Noticias/Detail?idNoticia=3164678&agencia=18&dataNoticia=2025-12-10%2009:18:05",
      "id": 3164678,
      "categoria": "Outros"
    }
  ]
}