{
  "ticker": "OFSA3",
  "total_dividendos": 7.4048,
  "periodo": "2015-2025",
  "quantidade_pagamentos": 23,
  "dividendos": [
    {
      "data_com": "2015-01-02",
      "valor": 0.067294,
      "tipo": "JRS CAP PROPRIO",
      "ano": 2015,
      "mes": 1,
      "dia": 2,
      "trimestre": "T1",
      "data_pagamento": "2014-12-30"
    },
    {
      "data_com": "2015-04-28",
      "valor": 0.181139,
      "tipo": "DIVIDENDO",
      "ano": 2015,
      "mes": 4,
      "dia": 28,
      "trimestre": "T2",
      "data_pagamento": "2015-04-28"
    },
    {
      "data_com": "2015-12-21",
      "valor": 0.09315,
      "tipo": "JRS CAP PROPRIO",
      "ano": 2015,
      "mes": 12,
      "dia": 21,
      "trimestre": "T4",
      "data_pagamento": "2015-12-21"
    },
    {
      "data_com": "2016-04-29",
      "valor": 0.224891,
      "tipo": "DIVIDENDO",
      "ano": 2016,
      "mes": 4,
      "dia": 29,
      "trimestre": "T2",
      "data_pagamento": "2016-04-29"
    },
    {
      "data_com": "2017-12-19",
      "valor": 0.11122,
      "tipo": "JRS CAP PROPRIO",
      "ano": 2017,
      "mes": 12,
      "dia": 19,
      "trimestre": "T4",
      "data_pagamento": "2017-12-14"
    },
    {
      "data_com": "2018-04-13",
      "valor": 0.102733,
      "tipo": "DIVIDENDO",
      "ano": 2018,
      "mes": 4,
      "dia": 13,
      "trimestre": "T2",
      "data_pagamento": "2018-04-13"
    },
    {
      "data_com": "2018-12-14",
      "valor": 0.14225,
      "tipo": "JRS CAP PROPRIO",
      "ano": 2018,
      "mes": 12,
      "dia": 14,
      "trimestre": "T4",
      "data_pagamento": "2018-12-11"
    },
    {
      "data_com": "2019-03-29",
      "valor": 0.177176,
      "tipo": "DIVIDENDO",
      "ano": 2019,
      "mes": 3,
      "dia": 29,
      "trimestre": "T1",
      "data_pagamento": "2019-03-29"
    },
    {
      "data_com": "2019-12-19",
      "valor": 0.01751,
      "tipo": "JRS CAP PROPRIO",
      "ano": 2019,
      "mes": 12,
      "dia": 19,
      "trimestre": "T4",
      "data_pagamento": "2019-12-16"
    },
    {
      "data_com": "2020-10-14",
      "valor": 0.188224,
      "tipo": "DIVIDENDO",
      "ano": 2020,
      "mes": 10,
      "dia": 14,
      "trimestre": "T4",
      "data_pagamento": "2020-10-08"
    },
    {
      "data_com": "2020-12-23",
      "valor": 0.25064,
      "tipo": "JRS CAP PROPRIO",
      "ano": 2020,
      "mes": 12,
      "dia": 23,
      "trimestre": "T4",
      "data_pagamento": "2020-12-18"
    },
    {
      "data_com": "2021-04-09",
      "valor": 0.173043,
      "tipo": "DIVIDENDO",
      "ano": 2021,
      "mes": 4,
      "dia": 9,
      "trimestre": "T2",
      "data_pagamento": "2021-04-09"
    },
    {
      "data_com": "2021-12-17",
      "valor": 0.30043,
      "tipo": "JRS CAP PROPRIO",
      "ano": 2021,
      "mes": 12,
      "dia": 17,
      "trimestre": "T4",
      "data_pagamento": "2021-12-14"
    },
    {
      "data_com": "2022-04-20",
      "valor": 0.237456,
      "tipo": "DIVIDENDO",
      "ano": 2022,
      "mes": 4,
      "dia": 20,
      "trimestre": "T2",
      "data_pagamento": "2022-04-20"
    },
    {
      "data_com": "2022-12-16",
      "valor": 0.438833,
      "tipo": "JRS CAP PROPRIO",
      "ano": 2022,
      "mes": 12,
      "dia": 16,
      "trimestre": "T4",
      "data_pagamento": "2022-12-13"
    },
    {
      "data_com": "2023-04-14",
      "valor": 0.196695,
      "tipo": "DIVIDENDO",
      "ano": 2023,
      "mes": 4,
      "dia": 14,
      "trimestre": "T2",
      "data_pagamento": "2023-04-14"
    },
    {
      "data_com": "2023-12-19",
      "valor": 0.276417,
      "tipo": "JRS CAP PROPRIO",
      "ano": 2023,
      "mes": 12,
      "dia": 19,
      "trimestre": "T4",
      "data_pagamento": "2023-12-14"
    },
    {
      "data_com": "2024-04-29",
      "valor": 0.336869,
      "tipo": "DIVIDENDO",
      "ano": 2024,
      "mes": 4,
      "dia": 29,
      "trimestre": "T2",
      "data_pagamento": "2024-04-29"
    },
    {
      "data_com": "2024-12-20",
      "valor": 0.576555,
      "tipo": "JRS CAP PROPRIO",
      "ano": 2024,
      "mes": 12,
      "dia": 20,
      "trimestre": "T4",
      "data_pagamento": "2024-12-17"
    },
    {
      "data_com": "2024-12-30",
      "valor": 2.231827,
      "tipo": "REST CAP DIN",
      "ano": 2024,
      "mes": 12,
      "dia": 30,
      "trimestre": "T4",
      "data_pagamento": "2024-10-29"
    },
    {
      "data_com": "2025-04-17",
      "valor": 0.092974,
      "tipo": "DIVIDENDO",
      "ano": 2025,
      "mes": 4,
      "dia": 17,
      "trimestre": "T2",
      "data_pagamento": "2025-04-17"
    },
    {
      "data_com": "2025-04-17",
      "valor": 0.057595,
      "tipo": "DIVIDENDO",
      "ano": 2025,
      "mes": 4,
      "dia": 17,
      "trimestre": "T2",
      "data_pagamento": "2025-04-17"
    },
    {
      "data_com": "2025-12-23",
      "valor": 0.929928,
      "tipo": "JRS CAP PROPRIO",
      "ano": 2025,
      "mes": 12,
      "dia": 23,
      "trimestre": "T4",
      "data_pagamento": "2025-12-16"
    }
  ]
}