{
  "empresa": {
    "ticker": "BALM",
    "nome": "BAUMER S.A.",
    "cnpj": "61.374.161/0001-30"
  },
  "ultima_atualizacao": "2026-01-03T09:19:37.807121",
  "total_noticias": 4,
  "noticias": [
    {
      "data": "2025-12-30",
      "data_hora": "2025-12-30 13:21:49",
      "titulo": " Calendario de Eventos Corporativos  ate 31/12/26",
      "headline": "BAUMER (BALM) - Calendario de Eventos Corporativos - ate 31/12/26",
      "conteudo": null,
      "url": "https://sistemasweb.b3.com.br/PlantaoNoticias/Noticias/Detail?idNoticia=3187967&agencia=18&dataNoticia=2025-12-30%2013:21:49",
      "id": 3187967,
      "categoria": "Outros"
    },
    {
      "data": "2025-12-15",
      "data_hora": "2025-12-15 13:48:19",
      "titulo": " Aviso aos Acionistas  12/12/25 (N)",
      "headline": "BAUMER (BALM) - Aviso aos Acionistas - 12/12/25 (N)",
      "conteudo": null,
      "url": "https://sistemasweb.b3.com.br/PlantaoNoticias/Noticias/Detail?idNoticia=3170115&agencia=18&dataNoticia=2025-12-15%2013:48:19",
      "id": 3170115,
      "categoria": "Aviso"
    },
    {
      "data": "2025-12-12",
      "data_hora": "2025-12-12 19:58:18",
      "titulo": " Aviso aos Acionistas  12/12/25",
      "headline": "BAUMER (BALM) - Aviso aos Acionistas - 12/12/25",
      "conteudo": null,
      "url": "https://sistemasweb.b3.com.br/PlantaoNoticias/Noticias/Detail?idNoticia=3169232&agencia=18&dataNoticia=2025-12-12%2019:58:18",
      "id": 3169232,
      "categoria": "Aviso"
    },
    {
      "data": "2025-12-12",
      "data_hora": "2025-12-12 19:56:16",
      "titulo": " Ata Reuniao do Conselho de Administracao  12/12/25",
      "headline": "BAUMER (BALM) - Ata Reuniao do Conselho de Administracao - 12/12/25",
      "conteudo": null,
      "url": "https://sistemasweb.b3.com.br/PlantaoNoticias/Noticias/Detail?idNoticia=3169230&agencia=18&dataNoticia=2025-12-12%2019:56:16",
      "id": 3169230,
      "categoria": "Governança"
    }
  ]
}