{
  "empresa": {
    "ticker": "SCAR",
    "nome": "SÃO CARLOS EMPREENDIMENTOS E PARTICIPAÇÕES S.A.",
    "cnpj": "29.780.061/0001-09"
  },
  "ultima_atualizacao": "2026-01-12T11:24:55.959594",
  "total_noticias": 4,
  "noticias": [
    {
      "data": "2026-01-09",
      "data_hora": "2026-01-09 14:14:43",
      "titulo": "NM)  VM Posicao Individual (Cia,Controladas e Coligadas)",
      "headline": "SAO CARLOS (SCAR-NM) - VM Posicao Individual (Cia,Controladas e Coligadas)",
      "conteudo": null,
      "url": "https://sistemasweb.b3.com.br/PlantaoNoticias/Noticias/Detail?idNoticia=3199921&agencia=18&dataNoticia=2026-01-09%2014:14:43",
      "id": 3199921,
      "categoria": "Outros"
    },
    {
      "data": "2026-01-05",
      "data_hora": "2026-01-05 08:00:07",
      "titulo": "NM)  Outros Comunicados ao Mercado  02/01/26",
      "headline": "SAO CARLOS (SCAR-NM) - Outros Comunicados ao Mercado - 02/01/26",
      "conteudo": null,
      "url": "https://sistemasweb.b3.com.br/PlantaoNoticias/Noticias/Detail?idNoticia=3192169&agencia=18&dataNoticia=2026-01-05%2008:00:07",
      "id": 3192169,
      "categoria": "Aviso"
    },
    {
      "data": "2026-01-05",
      "data_hora": "2026-01-05 08:00:06",
      "titulo": "NM)  Ata Reuniao do Conselho de Administracao  02/01/26",
      "headline": "SAO CARLOS (SCAR-NM) - Ata Reuniao do Conselho de Administracao - 02/01/26",
      "conteudo": null,
      "url": "https://sistemasweb.b3.com.br/PlantaoNoticias/Noticias/Detail?idNoticia=3192168&agencia=18&dataNoticia=2026-01-05%2008:00:06",
      "id": 3192168,
      "categoria": "Governança"
    },
    {
      "data": "2025-12-19",
      "data_hora": "2025-12-19 10:09:26",
      "titulo": "NM)  Apresentacao a analistas/agentes mercado  18/12/25",
      "headline": "SAO CARLOS (SCAR-NM) - Apresentacao a analistas/agentes mercado - 18/12/25",
      "conteudo": null,
      "url": "https://sistemasweb.b3.com.br/PlantaoNoticias/Noticias/Detail?idNoticia=3177588&agencia=18&dataNoticia=2025-12-19%2010:09:26",
      "id": 3177588,
      "categoria": "Governança"
    }
  ]
}