{
  "ticker": "RAIL3",
  "ultima_atualizacao": "2026-01-04T10:16:28.129920Z",
  "total_dividendos": 34,
  "dividendos": [
    {
      "data": "2025-06-16",
      "data_pagamento": "2025-06-11",
      "tipo": "DIVIDENDO",
      "valor": 0.810438,
      "status": "pago",
      "fonte": "b3_api"
    },
    {
      "data": "2024-04-30",
      "data_pagamento": "2024-04-30",
      "tipo": "DIVIDENDO",
      "valor": 0.092402,
      "status": "pago",
      "fonte": "b3_api"
    },
    {
      "data": "2023-04-19",
      "data_pagamento": "2023-04-19",
      "tipo": "DIVIDENDO",
      "valor": 0.066017,
      "status": "pago",
      "fonte": "b3_api"
    },
    {
      "data": "2022-04-27",
      "data_pagamento": "2022-04-27",
      "tipo": "DIVIDENDO",
      "valor": 0.019307,
      "status": "pago",
      "fonte": "b3_api"
    },
    {
      "data": "2014-04-10",
      "data_pagamento": "2014-04-10",
      "tipo": "DIVIDENDO",
      "valor": 0.004538,
      "status": "pago",
      "fonte": "b3_api"
    },
    {
      "data": "2013-04-17",
      "data_pagamento": "2013-04-17",
      "tipo": "DIVIDENDO",
      "valor": 0.082494,
      "status": "pago",
      "fonte": "b3_api"
    },
    {
      "data": "2012-04-27",
      "data_pagamento": "2012-04-27",
      "tipo": "DIVIDENDO",
      "valor": 0.08529,
      "status": "pago",
      "fonte": "b3_api"
    },
    {
      "data": "2011-05-05",
      "data_pagamento": "2011-05-05",
      "tipo": "DIVIDENDO",
      "valor": 0.082732,
      "status": "pago",
      "fonte": "b3_api"
    },
    {
      "data": "2010-04-30",
      "data_pagamento": "2010-04-30",
      "tipo": "DIVIDENDO",
      "valor": 0.010473,
      "status": "pago",
      "fonte": "b3_api"
    },
    {
      "data": "2010-04-30",
      "data_pagamento": "2010-04-30",
      "tipo": "DIVIDENDO",
      "valor": 0.002095,
      "status": "pago",
      "fonte": "b3_api"
    },
    {
      "data": "2010-04-30",
      "data_pagamento": "2010-04-30",
      "tipo": "DIVIDENDO",
      "valor": 0.002095,
      "status": "pago",
      "fonte": "b3_api"
    },
    {
      "data": "2009-04-29",
      "data_pagamento": "2009-04-29",
      "tipo": "DIVIDENDO",
      "valor": 0.014516,
      "status": "pago",
      "fonte": "b3_api"
    },
    {
      "data": "2009-04-29",
      "data_pagamento": "2009-04-29",
      "tipo": "DIVIDENDO",
      "valor": 0.014516,
      "status": "pago",
      "fonte": "b3_api"
    },
    {
      "data": "2009-04-29",
      "data_pagamento": "2009-04-29",
      "tipo": "DIVIDENDO",
      "valor": 0.072578,
      "status": "pago",
      "fonte": "b3_api"
    },
    {
      "data": "2008-04-28",
      "data_pagamento": "2008-04-28",
      "tipo": "DIVIDENDO",
      "valor": 0.017871,
      "status": "pago",
      "fonte": "b3_api"
    },
    {
      "data": "2008-04-28",
      "data_pagamento": "2008-04-28",
      "tipo": "DIVIDENDO",
      "valor": 0.089358,
      "status": "pago",
      "fonte": "b3_api"
    },
    {
      "data": "2008-04-28",
      "data_pagamento": "2008-04-28",
      "tipo": "DIVIDENDO",
      "valor": 0.017871,
      "status": "pago",
      "fonte": "b3_api"
    },
    {
      "data": "2007-04-02",
      "data_pagamento": "2007-04-02",
      "tipo": "DIVIDENDO",
      "valor": 0.00475,
      "status": "pago",
      "fonte": "b3_api"
    },
    {
      "data": "2007-04-02",
      "data_pagamento": "2007-04-02",
      "tipo": "DIVIDENDO",
      "valor": 0.00095,
      "status": "pago",
      "fonte": "b3_api"
    },
    {
      "data": "2007-04-02",
      "data_pagamento": "2007-04-02",
      "tipo": "DIVIDENDO",
      "valor": 0.00095,
      "status": "pago",
      "fonte": "b3_api"
    },
    {
      "data": "2007-01-02",
      "data_pagamento": "2006-12-29",
      "tipo": "JRS CAP PROPRIO",
      "valor": 0.005225,
      "status": "pago",
      "fonte": "b3_api"
    },
    {
      "data": "2007-01-02",
      "data_pagamento": "2006-12-29",
      "tipo": "JRS CAP PROPRIO",
      "valor": 0.026127,
      "status": "pago",
      "fonte": "b3_api"
    },
    {
      "data": "2007-01-02",
      "data_pagamento": "2006-12-29",
      "tipo": "JRS CAP PROPRIO",
      "valor": 0.005225,
      "status": "pago",
      "fonte": "b3_api"
    },
    {
      "data": "2006-03-27",
      "data_pagamento": "2006-03-27",
      "tipo": "DIVIDENDO",
      "valor": 0.455698,
      "status": "pago",
      "fonte": "b3_api"
    },
    {
      "data": "2006-03-27",
      "data_pagamento": "2006-03-27",
      "tipo": "DIVIDENDO",
      "valor": 0.09114,
      "status": "pago",
      "fonte": "b3_api"
    },
    {
      "data": "2006-03-27",
      "data_pagamento": "2006-03-27",
      "tipo": "DIVIDENDO",
      "valor": 0.09114,
      "status": "pago",
      "fonte": "b3_api"
    },
    {
      "data": "2005-12-29",
      "data_pagamento": "2005-12-27",
      "tipo": "JRS CAP PROPRIO",
      "valor": 0.0898,
      "status": "pago",
      "fonte": "b3_api"
    },
    {
      "data": "2005-12-29",
      "data_pagamento": "2005-12-27",
      "tipo": "JRS CAP PROPRIO",
      "valor": 0.0898,
      "status": "pago",
      "fonte": "b3_api"
    },
    {
      "data": "2005-12-29",
      "data_pagamento": "2005-12-27",
      "tipo": "JRS CAP PROPRIO",
      "valor": 0.449,
      "status": "pago",
      "fonte": "b3_api"
    },
    {
      "data": "2005-04-01",
      "data_pagamento": "2005-04-01",
      "tipo": "DIVIDENDO",
      "valor": 0.003515,
      "status": "pago",
      "fonte": "b3_api"
    },
    {
      "data": "2005-04-01",
      "data_pagamento": "2005-04-01",
      "tipo": "DIVIDENDO",
      "valor": 0.003515,
      "status": "pago",
      "fonte": "b3_api"
    },
    {
      "data": "2005-04-01",
      "data_pagamento": "2005-04-01",
      "tipo": "DIVIDENDO",
      "valor": 0.017576,
      "status": "pago",
      "fonte": "b3_api"
    },
    {
      "data": "2004-12-30",
      "data_pagamento": "2004-12-30",
      "tipo": "JRS CAP PROPRIO",
      "valor": 0.833354,
      "status": "pago",
      "fonte": "b3_api"
    },
    {
      "data": "2004-12-30",
      "data_pagamento": "2004-12-30",
      "tipo": "JRS CAP PROPRIO",
      "valor": 0.833354,
      "status": "pago",
      "fonte": "b3_api"
    }
  ],
  "estatisticas": {
    "total_bruto": 4.49,
    "total_ultimos_12m": 0.81,
    "quantidade_ultimos_12m": 1,
    "data_primeiro": "2004-12-30",
    "data_ultimo": "2025-06-16"
  }
}